jupyterlab_topbar_text/__init__.py
jupyterlab_topbar_text/_version.py
jupyterlab_topbar_text-1.1.0.data/data/share/jupyter/labextensions/jupyterlab-topbar-text/package.json
jupyterlab_topbar_text-1.1.0.data/data/share/jupyter/labextensions/jupyterlab-topbar-text/schemas/jupyterlab-topbar-text/package.json.orig
jupyterlab_topbar_text-1.1.0.data/data/share/jupyter/labextensions/jupyterlab-topbar-text/schemas/jupyterlab-topbar-text/plugin.json
jupyterlab_topbar_text-1.1.0.data/data/share/jupyter/labextensions/jupyterlab-topbar-text/static/218.9956ad086086b71703af.js
jupyterlab_topbar_text-1.1.0.data/data/share/jupyter/labextensions/jupyterlab-topbar-text/static/remoteEntry.e9874d13ad5997f4b07e.js
jupyterlab_topbar_text-1.1.0.data/data/share/jupyter/labextensions/jupyterlab-topbar-text/static/style.js
jupyterlab_topbar_text-1.1.0.data/data/share/jupyter/labextensions/jupyterlab-topbar-text/static/third-party-licenses.json
jupyterlab_topbar_text-1.1.0.data/data/share/jupyter/labextensions/jupyterlab-topbar-text/install.json
jupyterlab_topbar_text-1.1.0.dist-info/METADATA
jupyterlab_topbar_text-1.1.0.dist-info/WHEEL
jupyterlab_topbar_text-1.1.0.dist-info/licenses/LICENSE
jupyterlab_topbar_text-1.1.0.dist-info/RECORD
